{
  "indexes": [
    {
      "collectionGroup": "transfers",
      "queryScope": "COLLECTION",
      "fields": [
        { "fieldPath": "originStoreId", "order": "ASCENDING" },
        { "fieldPath": "createdAt", "order": "DESCENDING" }
      ]
    },
    {
      "collectionGroup": "history",
      "queryScope": "COLLECTION",
      "fields": [
        { "fieldPath": "visibleTo", "arrayConfig": "CONTAINS" },
        { "fieldPath": "createdAt", "order": "DESCENDING" }
      ]
    }
  ],
  "fieldOverrides": []
}
